hgpaktool/__init__.py
hgpaktool/api.py
hgpaktool/buffers.py
hgpaktool/cli.py
hgpaktool/compressors.py
hgpaktool/constants.py
hgpaktool/oodle.py
hgpaktool/os_funcs.py
hgpaktool/utils.py
hgpaktool/lib/README.md
hgpaktool-1.1.0.dist-info/licenses/LICENSE
hgpaktool-1.1.0.dist-info/METADATA
hgpaktool-1.1.0.dist-info/WHEEL
hgpaktool-1.1.0.dist-info/entry_points.txt
hgpaktool-1.1.0.dist-info/top_level.txt
hgpaktool-1.1.0.dist-info/RECORD
