Metadata-Version: 2.4
Name: hgpaktool
Version: 1.1.0
Summary: Tool for extracting data from NMS pak files
Author: monkeyman192
Maintainer: monkeyman192
License-Expression: MIT
Project-URL: homepage, https://github.com/monkeyman192/HGPAKtool
Project-URL: repository, https://github.com/monkeyman192/HGPAKtool.git
Keywords: modding
Classifier: Development Status :: 4 - Beta
Classifier: Operating System :: Microsoft
Classifier: Operating System :: MacOS
Classifier: Operating System :: Unix
Classifier: Programming Language :: Python :: 3.9
Classifier: Programming Language :: Python :: 3.10
Classifier: Programming Language :: Python :: 3.11
Classifier: Programming Language :: Python :: 3.12
Classifier: Programming Language :: Python :: 3.13
Classifier: Programming Language :: Python :: 3.14
Classifier: Programming Language :: Python :: 3 :: Only
Requires-Python: <4,>=3.9
License-File: LICENSE
Requires-Dist: zstandard
Requires-Dist: lz4
Provides-Extra: json5
Requires-Dist: json5; extra == "json5"
Provides-Extra: builder
Requires-Dist: pyinstaller; extra == "builder"
Dynamic: license-file
